media_type_version/__init__.py
media_type_version/__main__.py
media_type_version/defs.py
media_type_version/impl.py
media_type_version/py.typed
media_type_version/util.py
media_type_version-0.2.1.dist-info/METADATA
media_type_version-0.2.1.dist-info/WHEEL
media_type_version-0.2.1.dist-info/entry_points.txt
media_type_version-0.2.1.dist-info/licenses/LICENSES/BSD-2-Clause.txt
media_type_version-0.2.1.dist-info/RECORD
