Metadata-Version: 2.4
Name: media-type-version
Version: 0.2.1
Summary: Extract the format version from a media type string
Project-URL: Homepage, https://devel.ringlet.net/devel/media-type-version/
Project-URL: Changes, https://devel.ringlet.net/devel/media-type-version/changes/
Project-URL: Issue Tracker, https://gitlab.com/ppentchev/media-type-version/-/issues
Project-URL: Source Code, https://gitlab.com/ppentchev/media-type-version
Author-email: Peter Pentchev <roam@ringlet.net>
License-Expression: BSD-2-Clause
License-File: LICENSES/BSD-2-Clause.txt
Classifier: Development Status :: 4 - Beta
Classifier: Intended Audience :: Developers
Classifier: Operating System :: OS Independent
Classifier: Programming Language :: Python
Classifier: Programming Language :: Python :: 3
Classifier: Programming Language :: Python :: 3 :: Only
Classifier: Programming Language :: Python :: 3.11
Classifier: Programming Language :: Python :: 3.12
Classifier: Programming Language :: Python :: 3.13
Classifier: Programming Language :: Python :: 3.14
Classifier: Topic :: Software Development :: Libraries
Classifier: Topic :: Software Development :: Libraries :: Python Modules
Classifier: Topic :: Utilities
Classifier: Typing :: Typed
Requires-Python: >=3.11
